rtl/checkbit_calc.v
module checkbit_calc(
//Master inputs
input clk_i,
input rst_in,

//Control Inputs
input encoder_raw_data_ready_i,
input [15:0] encoder_data_i,

//Outputs 
output reg [11:0] cw_position_counts_o,
output reg [11:0] ccw_position_counts_o,
output reg [1:0] checkbit_result_o,
output reg data_ready_o,
output reg checkBit_NoError_o,
output reg checkBit_Error_o
);

//Internal Constants
parameter integer ccw_to_cw_position_conversion_c = 4095;
localparam integer ENCODER_VALUE_ST = 0,
		   CHECK_BIT_CALC_ST = 1,
		   VALIDATE_RESULT_ST = 2;

reg [2:0] state, nextstate;
reg encoder_raw_data_ready_rs;
reg [1:0] checkbit_result_ready_rs;
reg [11:0] data_rs;

//Fall egde encoder data ready detection
wire fe_encoder_raw_data_ready_rs;

//1st always block - Sequential always block
//state assignment always block, uses non-blocking
//assigment. Under reset, state is initialized 
//to "encoder_value_st". Otherwise state follows
//nextstate.
always@(posedge clk_i or negedge rst_in) begin
	if(!rst_in) begin
	       	state <= 3'b001;
		encoder_raw_data_ready_rs <= 1'b0;
	end 
	else begin
		state <= nextstate;
		//For falling edge detection,encoder_raw_data_ready_i is 
		//delayed by a clock
		encoder_raw_data_ready_rs <= encoder_raw_data_ready_i;
	end
end 

//Find falling edge of encoder_data_ready input
assign  fe_encoder_raw_data_ready_rs = ((~encoder_raw_data_ready_i) & (encoder_raw_data_ready_rs));

//Function to compute the checkbit result
function [1:0] CheckbitResult;
	input [15: 0] data;     //Input received data
	reg odd_parity;		//XOR of odd position bits in data
	reg even_parity;	//XOR of even position bits in data
	reg odd_checkbit;	//Final odd checkbit after XORing with received odd parity
	reg even_checkbit;	//Final even checkbit after XORing with received eveb parity
	integer i;
	begin
		//Initialization of signals used in the function
		odd_parity = 1'b0;
                even_parity = 1'b0;
		odd_checkbit = 1'b0;
		even_checkbit = 1'b0;
		
		//XORing of odd position bits in received data
		for (i = 0; i <= 6; i=i+1)
			odd_parity = (data[i * 2 + 1] ^ odd_parity);

		//XORing of even position bits in received data
                for (i = 0; i <= 6; i=i+1)
                        even_parity = (data[i * 2] ^ even_parity);

		//Odd Parity final check
		odd_checkbit  = ((!odd_parity) ^ data[15]);
		//Even Parity final check
		even_checkbit = ((!even_parity) ^ data[14]);
		
		//Concate even and odd parity
		CheckbitResult = {odd_checkbit,even_checkbit};
	end 
endfunction


//2nd always block - combination always block
//1. Manage state transition
//2. Uses blocking assignments
always@(*) begin
	//Default conditions
        nextstate = 3'b000;

	case(1'b1)
		state[ENCODER_VALUE_ST]: begin
		     //Upon falling edge of the encoder data ready, check
		     //whether encoder data is non-zero.
                     if((fe_encoder_raw_data_ready_rs == 1'b1) && (encoder_data_i != 0)) 
			     nextstate[CHECK_BIT_CALC_ST] = 1'b1;
		     else
			     nextstate[ENCODER_VALUE_ST] = 1'b1;
		end

		state[CHECK_BIT_CALC_ST] : begin
		     nextstate[VALIDATE_RESULT_ST] = 1'b1;
		end 

		state[VALIDATE_RESULT_ST] : begin
			nextstate[ENCODER_VALUE_ST] = 1'b1;
		end 

		default: begin
			nextstate = 3'b000;
		end 
	endcase 
end

//3rd Always block - Sequnetial
//1. Aiignement outputs based on the state
//2. Use non-blocking assignment
always @(posedge clk_i or negedge rst_in) begin
	if(!rst_in) begin
	   data_ready_o <= 1'b0;
   	   checkBit_Error_o <= 1'b0;
           checkBit_NoError_o <= 1'b0;
	   checkbit_result_o <= 2'b00;
	   data_rs <= 12'b0;
	   checkbit_result_ready_rs <= 2'b0;
           cw_position_counts_o <= 12'b0;
	   ccw_position_counts_o <= 12'b0;
	end 
	else begin
		//Default condition
		cw_position_counts_o <= data_rs;
		ccw_position_counts_o <= (4095 - data_rs);
		data_ready_o <= 1'b0;
	        checkBit_Error_o <= 1'b0;
         	checkBit_NoError_o <= 1'b0;
            	checkbit_result_o <= 2'b00;
		checkbit_result_ready_rs <= 2'b0;

		case(1'b1) 
			nextstate[CHECK_BIT_CALC_ST] : begin
			     //Call checkbit computation function to verify
			     //whether encoder received data is intact.
			     //as well report the computed checkbit value
			     checkbit_result_ready_rs <= CheckbitResult(encoder_data_i);
			end 
			nextstate[VALIDATE_RESULT_ST] : begin
			     //Ensure checkbit result is 0 to confirm no parity
			     //error, then copy the position value for further
			     //processing.
			     if(checkbit_result_ready_rs == 2'b0) begin
			 	data_rs <= encoder_data_i[13:2];  //Take a copy of the 12 bits
				data_ready_o <= 1'b1;
				checkBit_Error_o <= 1'b0;
				checkBit_NoError_o <= 1'b1;
			     end 
			     else begin
				data_ready_o <= 1'b0;
				checkBit_Error_o <= 1'b1;
				checkBit_NoError_o <= 1'b0;
			     end
	
			     checkbit_result_o <= checkbit_result_ready_rs;
			end

			default : begin
			     data_ready_o <= 1'b0;
			     checkBit_Error_o <= 1'b0;
			     checkBit_NoError_o <= 1'b0;
			     checkbit_result_o <= 2'b00;
			end	
		endcase
	end 
end 
endmodule

tb/checkbit_calc_tb.v
`timescale 1ns/1ps

module checkbit_calc_tb;

//Master inputs
reg clk_i;
reg rst_in;
//control Inputs
reg encoder_raw_data_ready_i;
reg [15:0] encoder_data_i;

//Outputs
wire [11:0] cw_position_counts_o;
wire [11:0] ccw_position_counts_o;
wire [1:0] checkbit_result_o;
wire data_ready_o;
wire checkBit_NoError_o;
wire checkBit_Error_o;

checkbit_calc uut(
	//Master inputs
	.clk_i(clk_i),
	.rst_in(rst_in),

	//Control Inputs
	.encoder_raw_data_ready_i(encoder_raw_data_ready_i),
	.encoder_data_i(encoder_data_i),

	 //Outputs
	.cw_position_counts_o(cw_position_counts_o),
	.ccw_position_counts_o(ccw_position_counts_o),
	.checkbit_result_o(checkbit_result_o),
	.data_ready_o(data_ready_o),
	.checkBit_NoError_o(checkBit_NoError_o),
	.checkBit_Error_o(checkBit_Error_o)
);

//Generate clock of 100MHz clock frequency
initial clk_i = 1'b0;
always #5 clk_i = ~clk_i;

initial begin

//Initialize input to DUT	
clk_i = 1'b0;
rst_in = 1'b0;
encoder_raw_data_ready_i = 1'b0;
encoder_data_i = 16'b0;

//Remove reset
#100 rst_in = 1'b1;

//@(posedge clk_i);
#100 encoder_data_i = 16'hBFF8;
encoder_raw_data_ready_i = 1'b1;
//repeat(4) @(posedge clk_i)
//@(posedge clk_i);
#100 encoder_raw_data_ready_i = 1'b0;
//repeat(4) @(posedge clk_i);

#100 encoder_data_i = 16'h7FF4;
encoder_raw_data_ready_i = 1'b1;
#100 encoder_raw_data_ready_i = 1'b0;

#100 encoder_data_i = 16'h3FF0;
encoder_raw_data_ready_i = 1'b1;
#100 encoder_raw_data_ready_i = 1'b0;

#100 encoder_data_i = 16'hBFEC;
encoder_raw_data_ready_i = 1'b1;
#100 encoder_raw_data_ready_i = 1'b0;

#100 encoder_data_i = 16'hFFE8;
encoder_raw_data_ready_i = 1'b1;
#100 encoder_raw_data_ready_i = 1'b0;

#100 encoder_data_i = 16'h3FE4;
encoder_raw_data_ready_i = 1'b1;
#100 encoder_raw_data_ready_i = 1'b0;

#100 encoder_data_i = 16'h7FE0;
encoder_raw_data_ready_i = 1'b1;
#100 encoder_raw_data_ready_i = 1'b0;

#100 encoder_data_i = 16'h7FDC;
encoder_raw_data_ready_i = 1'b1;
#100 encoder_raw_data_ready_i = 1'b0;

#100 encoder_data_i = 16'h3FD8;
encoder_raw_data_ready_i = 1'b1;
#100 encoder_raw_data_ready_i = 1'b0;

#100 encoder_data_i = 16'hFFD4;
encoder_raw_data_ready_i = 1'b1;
#100 encoder_raw_data_ready_i = 1'b0;

#100 encoder_data_i = 16'hBFD0;
encoder_raw_data_ready_i = 1'b1;
#100 encoder_raw_data_ready_i = 1'b0;

#100 encoder_data_i = 16'h3FCC;
encoder_raw_data_ready_i = 1'b1;
#100 encoder_raw_data_ready_i = 1'b0;

#100 encoder_data_i = 16'h7FC8;
encoder_raw_data_ready_i = 1'b1;
#100 encoder_raw_data_ready_i = 1'b0;

#100 encoder_data_i = 16'hBFC4;
encoder_raw_data_ready_i = 1'b1;
#100 encoder_raw_data_ready_i = 1'b0;

#100 encoder_data_i = 16'hFFC0;
encoder_raw_data_ready_i = 1'b1;
#100 encoder_raw_data_ready_i = 1'b0;

#100 encoder_data_i = 16'hBFBC;
encoder_raw_data_ready_i = 1'b1;
#100 encoder_raw_data_ready_i = 1'b0;

end 

//Monitor each input and output
initial begin
$monitor("Time=%0t | rst_in=%b encoder_raw_data_ready_i=%b encoder_data_i=%h | data_ready_o=%b  checkbit_result_o=%b cw_position_counts_o =%h ccw_position_counts_o = %h", $time, rst_in, encoder_raw_data_ready_i, encoder_data_i, data_ready_o, checkbit_result_o, cw_position_counts_o, ccw_position_counts_o);

end

//Waveform dump
initial begin
  $dumpfile("sim/waveforms/checkbit_calc.vcd");  // MUST match Makefile
  $dumpvars(0, checkbit_calc_tb);

  #9000 $finish;
end

endmodule

sim/waveforms/checkbit_calc.vcd
$date
	Sun May  3 17:37:03 2026
$end
$version
	Icarus Verilog
$end
$timescale
	1ps
$end
$scope module checkbit_calc_tb $end
$var wire 1 ! data_ready_o $end
$var wire 12 " cw_position_counts_o [11:0] $end
$var wire 2 # checkbit_result_o [1:0] $end
$var wire 1 $ checkBit_NoError_o $end
$var wire 1 % checkBit_Error_o $end
$var wire 12 & ccw_position_counts_o [11:0] $end
$var reg 1 ' clk_i $end
$var reg 16 ( encoder_data_i [15:0] $end
$var reg 1 ) encoder_raw_data_ready_i $end
$var reg 1 * rst_in $end
$scope module uut $end
$var wire 1 ' clk_i $end
$var wire 16 + encoder_data_i [15:0] $end
$var wire 1 ) encoder_raw_data_ready_i $end
$var wire 1 , fe_encoder_raw_data_ready_rs $end
$var wire 1 * rst_in $end
$var parameter 32 - CHECK_BIT_CALC_ST $end
$var parameter 32 . ENCODER_VALUE_ST $end
$var parameter 32 / VALIDATE_RESULT_ST $end
$var parameter 32 0 ccw_to_cw_position_conversion_c $end
$var reg 12 1 ccw_position_counts_o [11:0] $end
$var reg 1 % checkBit_Error_o $end
$var reg 1 $ checkBit_NoError_o $end
$var reg 2 2 checkbit_result_o [1:0] $end
$var reg 2 3 checkbit_result_ready_rs [1:0] $end
$var reg 12 4 cw_position_counts_o [11:0] $end
$var reg 1 ! data_ready_o $end
$var reg 12 5 data_rs [11:0] $end
$var reg 1 6 encoder_raw_data_ready_rs $end
$var reg 3 7 nextstate [2:0] $end
$var reg 3 8 state [2:0] $end
$scope function CheckbitResult $end
$var reg 16 9 data [15:0] $end
$var reg 1 : even_checkbit $end
$var reg 1 ; even_parity $end
$var reg 1 < odd_checkbit $end
$var reg 1 = odd_parity $end
$var integer 32 > i [31:0] $end
$upscope $end
$upscope $end
$upscope $end
$enddefinitions $end
$comment Show the parameter values. $end
$dumpall
b111111111111 0
b10 /
b0 .
b1 -
$end
#0
$dumpvars
bx >
x=
x<
x;
x:
bx 9
b1 8
b1 7
06
b0 5
b0 4
b0 3
b0 2
b0 1
0,
b0 +
0*
0)
b0 (
0'
b0 &
0%
0$
b0 #
b0 "
0!
$end
#5000
1'
#10000
0'
#15000
1'
#20000
0'
#25000
1'
#30000
0'
#35000
1'
#40000
0'
#45000
1'
#50000
0'
#55000
1'
#60000
0'
#65000
1'
#70000
0'
#75000
1'
#80000
0'
#85000
1'
#90000
0'
#95000
1'
#100000
0'
1*
#105000
b111111111111 &
b111111111111 1
1'
#110000
0'
#115000
1'
#120000
0'
#125000
1'
#130000
0'
#135000
1'
#140000
0'
#145000
1'
#150000
0'
#155000
1'
#160000
0'
#165000
1'
#170000
0'
#175000
1'
#180000
0'
#185000
1'
#190000
0'
#195000
1'
#200000
b1 7
0'
1)
b1011111111111000 (
b1011111111111000 +
#205000
16
1'
#210000
0'
#215000
1'
#220000
0'
#225000
1'
#230000
0'
#235000
1'
#240000
0'
#245000
1'
#250000
0'
#255000
1'
#260000
0'
#265000
1'
#270000
0'
#275000
1'
#280000
0'
#285000
1'
#290000
0'
#295000
1'
#300000
b10 7
1,
0'
0)
#305000
0,
b100 7
06
b10 8
b111 >
0:
0<
1;
0=
b1011111111111000 9
1'
#310000
0'
#315000
b1 7
b100 8
1$
1!
b111111111110 5
1'
#320000
0'
#325000
b1 7
0$
0!
b1 &
b1 1
b111111111110 "
b111111111110 4
b1 8
1'
#330000
0'
#335000
1'
#340000
0'
#345000
1'
#350000
0'
#355000
1'
#360000
0'
#365000
1'
#370000
0'
#375000
1'
#380000
0'
#385000
1'
#390000
0'
#395000
1'
#400000
b1 7
0'
1)
b111111111110100 (
b111111111110100 +
#405000
16
1'
#410000
0'
#415000
1'
#420000
0'
#425000
1'
#430000
0'
#435000
1'
#440000
0'
#445000
1'
#450000
0'
#455000
1'
#460000
0'
#465000
1'
#470000
0'
#475000
1'
#480000
0'
#485000
1'
#490000
0'
#495000
1'
#500000
b10 7
1,
0'
0)
#505000
0,
b100 7
06
b10 8
1=
b111 >
0;
b111111111110100 9
1'
#510000
0'
#515000
b1 7
b100 8
1$
1!
b111111111101 5
1'
#520000
0'
#525000
b1 7
0$
0!
b10 &
b10 1
b111111111101 "
b111111111101 4
b1 8
1'
#530000
0'
#535000
1'
#540000
0'
#545000
1'
#550000
0'
#555000
1'
#560000
0'
#565000
1'
#570000
0'
#575000
1'
#580000
0'
#585000
1'
#590000
0'
#595000
1'
#600000
b1 7
0'
1)
b11111111110000 (
b11111111110000 +
#605000
16
1'
#610000
0'
#615000
1'
#620000
0'
#625000
1'
#630000
0'
#635000
1'
#640000
0'
#645000
1'
#650000
0'
#655000
1'
#660000
0'
#665000
1'
#670000
0'
#675000
1'
#680000
0'
#685000
1'
#690000
0'
#695000
1'
#700000
b10 7
1,
0'
0)
#705000
0,
b100 7
06
b10 8
1;
b111 >
1=
b11111111110000 9
1'
#710000
0'
#715000
b1 7
b100 8
1$
1!
b111111111100 5
1'
#720000
0'
#725000
b1 7
0$
0!
b11 &
b11 1
b111111111100 "
b111111111100 4
b1 8
1'
#730000
0'
#735000
1'
#740000
0'
#745000
1'
#750000
0'
#755000
1'
#760000
0'
#765000
1'
#770000
0'
#775000
1'
#780000
0'
#785000
1'
#790000
0'
#795000
1'
#800000
b1 7
0'
1)
b1011111111101100 (
b1011111111101100 +
#805000
16
1'
#810000
0'
#815000
1'
#820000
0'
#825000
1'
#830000
0'
#835000
1'
#840000
0'
#845000
1'
#850000
0'
#855000
1'
#860000
0'
#865000
1'
#870000
0'
#875000
1'
#880000
0'
#885000
1'
#890000
0'
#895000
1'
#900000
b10 7
1,
0'
0)
#905000
0,
b100 7
06
b10 8
b111 >
1;
0=
b1011111111101100 9
1'
#910000
0'
#915000
b1 7
b100 8
1$
1!
b111111111011 5
1'
#920000
0'
#925000
b1 7
0$
0!
b100 &
b100 1
b111111111011 "
b111111111011 4
b1 8
1'
#930000
0'
#935000
1'
#940000
0'
#945000
1'
#950000
0'
#955000
1'
#960000
0'
#965000
1'
#970000
0'
#975000
1'
#980000
0'
#985000
1'
#990000
0'
#995000
1'
#1000000
b1 7
0'
1)
b1111111111101000 (
b1111111111101000 +
#1005000
16
1'
#1010000
0'
#1015000
1'
#1020000
0'
#1025000
1'
#1030000
0'
#1035000
1'
#1040000
0'
#1045000
1'
#1050000
0'
#1055000
1'
#1060000
0'
#1065000
1'
#1070000
0'
#1075000
1'
#1080000
0'
#1085000
1'
#1090000
0'
#1095000
1'
#1100000
b10 7
1,
0'
0)
#1105000
0,
b100 7
06
b10 8
0=
b111 >
0;
b1111111111101000 9
1'
#1110000
0'
#1115000
b1 7
b100 8
1$
1!
b111111111010 5
1'
#1120000
0'
#1125000
b1 7
0$
0!
b101 &
b101 1
b111111111010 "
b111111111010 4
b1 8
1'
#1130000
0'
#1135000
1'
#1140000
0'
#1145000
1'
#1150000
0'
#1155000
1'
#1160000
0'
#1165000
1'
#1170000
0'
#1175000
1'
#1180000
0'
#1185000
1'
#1190000
0'
#1195000
1'
#1200000
b1 7
0'
1)
b11111111100100 (
b11111111100100 +
#1205000
16
1'
#1210000
0'
#1215000
1'
#1220000
0'
#1225000
1'
#1230000
0'
#1235000
1'
#1240000
0'
#1245000
1'
#1250000
0'
#1255000
1'
#1260000
0'
#1265000
1'
#1270000
0'
#1275000
1'
#1280000
0'
#1285000
1'
#1290000
0'
#1295000
1'
#1300000
b10 7
1,
0'
0)
#1305000
0,
b100 7
06
b10 8
1;
1=
b111 >
b11111111100100 9
1'
#1310000
0'
#1315000
b1 7
b100 8
1$
1!
b111111111001 5
1'
#1320000
0'
#1325000
b1 7
0$
0!
b110 &
b110 1
b111111111001 "
b111111111001 4
b1 8
1'
#1330000
0'
#1335000
1'
#1340000
0'
#1345000
1'
#1350000
0'
#1355000
1'
#1360000
0'
#1365000
1'
#1370000
0'
#1375000
1'
#1380000
0'
#1385000
1'
#1390000
0'
#1395000
1'
#1400000
b1 7
0'
1)
b111111111100000 (
b111111111100000 +
#1405000
16
1'
#1410000
0'
#1415000
1'
#1420000
0'
#1425000
1'
#1430000
0'
#1435000
1'
#1440000
0'
#1445000
1'
#1450000
0'
#1455000
1'
#1460000
0'
#1465000
1'
#1470000
0'
#1475000
1'
#1480000
0'
#1485000
1'
#1490000
0'
#1495000
1'
#1500000
b10 7
1,
0'
0)
#1505000
0,
b100 7
06
b10 8
b111 >
0;
1=
b111111111100000 9
1'
#1510000
0'
#1515000
b1 7
b100 8
1$
1!
b111111111000 5
1'
#1520000
0'
#1525000
b1 7
0$
0!
b111 &
b111 1
b111111111000 "
b111111111000 4
b1 8
1'
#1530000
0'
#1535000
1'
#1540000
0'
#1545000
1'
#1550000
0'
#1555000
1'
#1560000
0'
#1565000
1'
#1570000
0'
#1575000
1'
#1580000
0'
#1585000
1'
#1590000
0'
#1595000
1'
#1600000
b1 7
0'
1)
b111111111011100 (
b111111111011100 +
#1605000
16
1'
#1610000
0'
#1615000
1'
#1620000
0'
#1625000
1'
#1630000
0'
#1635000
1'
#1640000
0'
#1645000
1'
#1650000
0'
#1655000
1'
#1660000
0'
#1665000
1'
#1670000
0'
#1675000
1'
#1680000
0'
#1685000
1'
#1690000
0'
#1695000
1'
#1700000
b10 7
1,
0'
0)
#1705000
0,
b100 7
06
b10 8
0;
b111 >
1=
b111111111011100 9
1'
#1710000
0'
#1715000
b1 7
b100 8
1$
1!
b111111110111 5
1'
#1720000
0'
#1725000
b1 7
0$
0!
b1000 &
b1000 1
b111111110111 "
b111111110111 4
b1 8
1'
#1730000
0'
#1735000
1'
#1740000
0'
#1745000
1'
#1750000
0'
#1755000
1'
#1760000
0'
#1765000
1'
#1770000
0'
#1775000
1'
#1780000
0'
#1785000
1'
#1790000
0'
#1795000
1'
#1800000
b1 7
0'
1)
b11111111011000 (
b11111111011000 +
#1805000
16
1'
#1810000
0'
#1815000
1'
#1820000
0'
#1825000
1'
#1830000
0'
#1835000
1'
#1840000
0'
#1845000
1'
#1850000
0'
#1855000
1'
#1860000
0'
#1865000
1'
#1870000
0'
#1875000
1'
#1880000
0'
#1885000
1'
#1890000
0'
#1895000
1'
#1900000
b10 7
1,
0'
0)
#1905000
0,
b100 7
06
b10 8
1;
b111 >
1=
b11111111011000 9
1'
#1910000
0'
#1915000
b1 7
b100 8
1$
1!
b111111110110 5
1'
#1920000
0'
#1925000
b1 7
0$
0!
b1001 &
b1001 1
b111111110110 "
b111111110110 4
b1 8
1'
#1930000
0'
#1935000
1'
#1940000
0'
#1945000
1'
#1950000
0'
#1955000
1'
#1960000
0'
#1965000
1'
#1970000
0'
#1975000
1'
#1980000
0'
#1985000
1'
#1990000
0'
#1995000
1'
#2000000
b1 7
0'
1)
b1111111111010100 (
b1111111111010100 +
#2005000
16
1'
#2010000
0'
#2015000
1'
#2020000
0'
#2025000
1'
#2030000
0'
#2035000
1'
#2040000
0'
#2045000
1'
#2050000
0'
#2055000
1'
#2060000
0'
#2065000
1'
#2070000
0'
#2075000
1'
#2080000
0'
#2085000
1'
#2090000
0'
#2095000
1'
#2100000
b10 7
1,
0'
0)
#2105000
0,
b100 7
06
b10 8
b111 >
0;
0=
b1111111111010100 9
1'
#2110000
0'
#2115000
b1 7
b100 8
1$
1!
b111111110101 5
1'
#2120000
0'
#2125000
b1 7
0$
0!
b1010 &
b1010 1
b111111110101 "
b111111110101 4
b1 8
1'
#2130000
0'
#2135000
1'
#2140000
0'
#2145000
1'
#2150000
0'
#2155000
1'
#2160000
0'
#2165000
1'
#2170000
0'
#2175000
1'
#2180000
0'
#2185000
1'
#2190000
0'
#2195000
1'
#2200000
b1 7
0'
1)
b1011111111010000 (
b1011111111010000 +
#2205000
16
1'
#2210000
0'
#2215000
1'
#2220000
0'
#2225000
1'
#2230000
0'
#2235000
1'
#2240000
0'
#2245000
1'
#2250000
0'
#2255000
1'
#2260000
0'
#2265000
1'
#2270000
0'
#2275000
1'
#2280000
0'
#2285000
1'
#2290000
0'
#2295000
1'
#2300000
b10 7
1,
0'
0)
#2305000
0,
b100 7
06
b10 8
1;
0=
b111 >
b1011111111010000 9
1'
#2310000
0'
#2315000
b1 7
b100 8
1$
1!
b111111110100 5
1'
#2320000
0'
#2325000
b1 7
0$
0!
b1011 &
b1011 1
b111111110100 "
b111111110100 4
b1 8
1'
#2330000
0'
#2335000
1'
#2340000
0'
#2345000
1'
#2350000
0'
#2355000
1'
#2360000
0'
#2365000
1'
#2370000
0'
#2375000
1'
#2380000
0'
#2385000
1'
#2390000
0'
#2395000
1'
#2400000
b1 7
0'
1)
b11111111001100 (
b11111111001100 +
#2405000
16
1'
#2410000
0'
#2415000
1'
#2420000
0'
#2425000
1'
#2430000
0'
#2435000
1'
#2440000
0'
#2445000
1'
#2450000
0'
#2455000
1'
#2460000
0'
#2465000
1'
#2470000
0'
#2475000
1'
#2480000
0'
#2485000
1'
#2490000
0'
#2495000
1'
#2500000
b10 7
1,
0'
0)
#2505000
0,
b100 7
06
b10 8
1=
b111 >
1;
b11111111001100 9
1'
#2510000
0'
#2515000
b1 7
b100 8
1$
1!
b111111110011 5
1'
#2520000
0'
#2525000
b1 7
0$
0!
b1100 &
b1100 1
b111111110011 "
b111111110011 4
b1 8
1'
#2530000
0'
#2535000
1'
#2540000
0'
#2545000
1'
#2550000
0'
#2555000
1'
#2560000
0'
#2565000
1'
#2570000
0'
#2575000
1'
#2580000
0'
#2585000
1'
#2590000
0'
#2595000
1'
#2600000
b1 7
0'
1)
b111111111001000 (
b111111111001000 +
#2605000
16
1'
#2610000
0'
#2615000
1'
#2620000
0'
#2625000
1'
#2630000
0'
#2635000
1'
#2640000
0'
#2645000
1'
#2650000
0'
#2655000
1'
#2660000
0'
#2665000
1'
#2670000
0'
#2675000
1'
#2680000
0'
#2685000
1'
#2690000
0'
#2695000
1'
#2700000
b10 7
1,
0'
0)
#2705000
0,
b100 7
06
b10 8
b111 >
0;
1=
b111111111001000 9
1'
#2710000
0'
#2715000
b1 7
b100 8
1$
1!
b111111110010 5
1'
#2720000
0'
#2725000
b1 7
0$
0!
b1101 &
b1101 1
b111111110010 "
b111111110010 4
b1 8
1'
#2730000
0'
#2735000
1'
#2740000
0'
#2745000
1'
#2750000
0'
#2755000
1'
#2760000
0'
#2765000
1'
#2770000
0'
#2775000
1'
#2780000
0'
#2785000
1'
#2790000
0'
#2795000
1'
#2800000
b1 7
0'
1)
b1011111111000100 (
b1011111111000100 +
#2805000
16
1'
#2810000
0'
#2815000
1'
#2820000
0'
#2825000
1'
#2830000
0'
#2835000
1'
#2840000
0'
#2845000
1'
#2850000
0'
#2855000
1'
#2860000
0'
#2865000
1'
#2870000
0'
#2875000
1'
#2880000
0'
#2885000
1'
#2890000
0'
#2895000
1'
#2900000
b10 7
1,
0'
0)
#2905000
0,
b100 7
06
b10 8
1;
b111 >
0=
b1011111111000100 9
1'
#2910000
0'
#2915000
b1 7
b100 8
1$
1!
b111111110001 5
1'
#2920000
0'
#2925000
b1 7
0$
0!
b1110 &
b1110 1
b111111110001 "
b111111110001 4
b1 8
1'
#2930000
0'
#2935000
1'
#2940000
0'
#2945000
1'
#2950000
0'
#2955000
1'
#2960000
0'
#2965000
1'
#2970000
0'
#2975000
1'
#2980000
0'
#2985000
1'
#2990000
0'
#2995000
1'
#3000000
b1 7
0'
1)
b1111111111000000 (
b1111111111000000 +
#3005000
16
1'
#3010000
0'
#3015000
1'
#3020000
0'
#3025000
1'
#3030000
0'
#3035000
1'
#3040000
0'
#3045000
1'
#3050000
0'
#3055000
1'
#3060000
0'
#3065000
1'
#3070000
0'
#3075000
1'
#3080000
0'
#3085000
1'
#3090000
0'
#3095000
1'
#3100000
b10 7
1,
0'
0)
#3105000
0,
b100 7
06
b10 8
0=
b111 >
0;
b1111111111000000 9
1'
#3110000
0'
#3115000
b1 7
b100 8
1$
1!
b111111110000 5
1'
#3120000
0'
#3125000
b1 7
0$
0!
b1111 &
b1111 1
b111111110000 "
b111111110000 4
b1 8
1'
#3130000
0'
#3135000
1'
#3140000
0'
#3145000
1'
#3150000
0'
#3155000
1'
#3160000
0'
#3165000
1'
#3170000
0'
#3175000
1'
#3180000
0'
#3185000
1'
#3190000
0'
#3195000
1'
#3200000
b1 7
0'
1)
b1011111110111100 (
b1011111110111100 +
#3205000
16
1'
#3210000
0'
#3215000
1'
#3220000
0'
#3225000
1'
#3230000
0'
#3235000
1'
#3240000
0'
#3245000
1'
#3250000
0'
#3255000
1'
#3260000
0'
#3265000
1'
#3270000
0'
#3275000
1'
#3280000
0'
#3285000
1'
#3290000
0'
#3295000
1'
#3300000
b10 7
1,
0'
0)
#3305000
0,
b100 7
06
b10 8
1;
0=
b111 >
b1011111110111100 9
1'
#3310000
0'
#3315000
b1 7
b100 8
1$
1!
b111111101111 5
1'
#3320000
0'
#3325000
b1 7
0$
0!
b10000 &
b10000 1
b111111101111 "
b111111101111 4
b1 8
1'
